{"_ts":[1543650667],"_r":{"breakdown":{"html":{"bytes":[73987],"requests":[2]},"js":{"bytes":[262077],"requests":[8]},"css":{"bytes":[48612],"requests":[1]},"image":{"bytes":[845080],"requests":[44]},"flash":{"bytes":[0],"requests":[0]},"font":{"bytes":[296243],"requests":[4]},"video":{"bytes":[0],"requests":[0]},"other":{"bytes":[1116],"requests":[1]}},"date":[1543650667],"domElements":[4122],"domInteractive":[4056],"firstPaint":[2798.3999999997],"fullyLoaded":[12547],"id":["181201_ES_f87ef0b15c11467ab056bb9e492eb375"],"loadTime":[10437],"render":[3633],"SpeedIndex":[4523],"TTFB":[1765],"videoFrames":[[{"_i":"ms_000000.jpg","_t":0,"_vc":0},{"_i":"ms_003633.jpg","_t":3633,"_vc":33},{"_i":"ms_004033.jpg","_t":4033,"_vc":33},{"_i":"ms_004067.jpg","_t":4067,"_vc":33},{"_i":"ms_004100.jpg","_t":4100,"_vc":34},{"_i":"ms_004167.jpg","_t":4167,"_vc":34},{"_i":"ms_004200.jpg","_t":4200,"_vc":34},{"_i":"ms_004233.jpg","_t":4233,"_vc":33},{"_i":"ms_004367.jpg","_t":4367,"_vc":53},{"_i":"ms_004500.jpg","_t":4500,"_vc":63},{"_i":"ms_004800.jpg","_t":4800,"_vc":69},{"_i":"ms_004833.jpg","_t":4833,"_vc":69},{"_i":"ms_004867.jpg","_t":4867,"_vc":69},{"_i":"ms_004900.jpg","_t":4900,"_vc":69},{"_i":"ms_004933.jpg","_t":4933,"_vc":69},{"_i":"ms_005433.jpg","_t":5433,"_vc":83},{"_i":"ms_005567.jpg","_t":5567,"_vc":100},{"_i":"ms_005767.jpg","_t":5767,"_vc":99},{"_i":"ms_006300.jpg","_t":6300,"_vc":99},{"_i":"ms_006333.jpg","_t":6333,"_vc":99},{"_i":"ms_006367.jpg","_t":6367,"_vc":99},{"_i":"ms_006400.jpg","_t":6400,"_vc":100},{"_i":"ms_006467.jpg","_t":6467,"_vc":100},{"_i":"ms_007333.jpg","_t":7333,"_vc":99},{"_i":"ms_007433.jpg","_t":7433,"_vc":100},{"_i":"ms_007467.jpg","_t":7467,"_vc":100}]],"visualComplete":[5567],"lighthouse":[57],"pagespeed":[95]}}